pyChatango/__init__.py
pyChatango/pyChatango.py
pyChatango/tempDir.py
pychatango_dev-0.1.1.dist-info/LICENSE
pychatango_dev-0.1.1.dist-info/METADATA
pychatango_dev-0.1.1.dist-info/WHEEL
pychatango_dev-0.1.1.dist-info/top_level.txt
pychatango_dev-0.1.1.dist-info/RECORD
