Metadata-Version: 2.1
Name: pychatango-dev
Version: 0.1.1
Summary: Send messages to Chatango chatrooms
Home-page: https://github.com/raishid/pyChatango
Author: Raishid
Author-email: raishidavid@gmail.com
License-File: LICENSE
Requires-Dist: playwright
